inspectnn/BaseLayer.py
inspectnn/SoftmaxLayer.py
inspectnn/__init__.py
inspectnn/Add/AddLayer.py
inspectnn/Add/Add_kernel_tflite.py
inspectnn/Add/__init__.py
inspectnn/Add/libAddTexture.so
inspectnn/Concatenate/ConcatenateLayer.py
inspectnn/Concatenate/__init__.py
inspectnn/Conv/ConvLayer.py
inspectnn/Conv/ConvLayer_TFLITE.py
inspectnn/Conv/Conv_cuda.py
inspectnn/Conv/Conv_kernel_tflite.py
inspectnn/Conv/__init__.py
inspectnn/Conv/libconvolutionTexture.so
inspectnn/Dataset/Dataset_FGVC7.py
inspectnn/Dataset/Dataset_GattidmvsCani.py
inspectnn/Dataset/Dataset_cifar10.py
inspectnn/Dataset/Dataset_cifar100.py
inspectnn/Dataset/Dataset_mnist.py
inspectnn/Dataset/__init__.py
inspectnn/Dense/DenseLayer.py
inspectnn/Dense/DenseLayer_TFLITE.py
inspectnn/Dense/Dense_cuda.py
inspectnn/Dense/Dense_kernel_tflite.py
inspectnn/Dense/__init__.py
inspectnn/Dense/matrixMul.so
inspectnn/Flatten/FlattenLayer.py
inspectnn/Flatten/__init__.py
inspectnn/Mean/MeanLayer.py
inspectnn/Mean/MeanLayer_TFLITE.py
inspectnn/Mean/Mean_kernel.py
inspectnn/Mean/__init__.py
inspectnn/Model/BaseModel.py
inspectnn/Model/BaseModel_tflite.py
inspectnn/Model/GenericModel_tflite.py
inspectnn/Model/NetworkModel.py
inspectnn/Model/NetworkModel_tflite.py
inspectnn/Model/__init__.py
inspectnn/PAD/PadLayer.py
inspectnn/PAD/Pad_kernel_tflite.py
inspectnn/PAD/__init__.py
inspectnn/Pooling/Pool_cuda.py
inspectnn/Pooling/Pool_kernel.py
inspectnn/Pooling/PoolingLayer.py
inspectnn/Pooling/PoolingLayer_TFLITE.py
inspectnn/Pooling/__init__.py
inspectnn/Pooling/poolMul.so
inspectnn/Quantizate/Quant_kernel_tflite.py
inspectnn/Quantizate/QuantizateLayer.py
inspectnn/Quantizate/__init__.py
inspectnn/Reshape/ReshapeLayer.py
inspectnn/Reshape/Reshape_kernel_tflite.py
inspectnn/Reshape/__init__.py
inspectnn/Utils/__init__.py
inspectnn/Utils/utils.py
inspectnn-0.6.1.dist-info/METADATA
inspectnn-0.6.1.dist-info/WHEEL
inspectnn-0.6.1.dist-info/top_level.txt
inspectnn-0.6.1.dist-info/RECORD
