Metadata-Version: 2.1
Name: inspectnn
Version: 0.6.1
Summary: Inference eNgine uSing aPproximate arithmEtic ComponenTs for Neural Networks
Home-page: https://github.com/SalvatoreBarone/inspect-nn
Author: Salvatore Barone, Filippo Ferrandino
Author-email: salvatore.barone@unina.it, filippo.ferrandino@unina.it
Project-URL: Bug Reports, https://github.com/SalvatoreBarone/inspect-nn/issues
Project-URL: Source, https://github.com/SalvatoreBarone/inspect-nn
Keywords: Neural Networks Approximate-Computing
Classifier: Intended Audience :: Information Technology
Classifier: Intended Audience :: Science/Research
Classifier: Topic :: Scientific/Engineering :: Artificial Intelligence
Classifier: License :: OSI Approved :: GNU General Public License v3 or later (GPLv3+)
Classifier: Programming Language :: Python :: 3.11
Requires-Python: >=3.11
Requires-Dist: tensorflow >=2.13.0
Requires-Dist: protobuf
Requires-Dist: numpy >=1.23
Requires-Dist: numba >=0.58.0
Requires-Dist: scikit-learn
